pylabeledrf/__init__.py
pylabeledrf/computeLRF.py
test/__init__.py
test/test_computeLRF.py
pylabeledrf-0.3.2.dist-info/LICENSE
pylabeledrf-0.3.2.dist-info/METADATA
pylabeledrf-0.3.2.dist-info/WHEEL
pylabeledrf-0.3.2.dist-info/top_level.txt
pylabeledrf-0.3.2.dist-info/RECORD
