Metadata-Version: 2.1
Name: pylabeledrf
Version: 0.3.2
Summary: A package to compute the Robinson Fould distance extended to labeled topologies.
Home-page: https://github.com/dessimozlab/pylabeledrf
Download-URL: https://github.com/DessimozLab/pylabeledrf/archive/v0.2.2.tar.gz
Author: Christophe Dessimoz
Author-email: christophe.dessimoz@unil.ch
Classifier: Programming Language :: Python :: 3
Classifier: License :: OSI Approved :: MIT License
Classifier: Operating System :: OS Independent
License-File: LICENSE
Requires-Dist: dendropy >=4
